Workbook

Sheet 1、收入结余表
B2: 2026 | C2: 年终奖 | D2: 工资 | E2: 业绩奖金 | F2: 副业收入 | G2: 存款利息 | H2: 投资收益 | I2: 其他 | J2: 总收入 | K2: 总支出 | L2: 结余 | M2: 储蓄率 | N2: 总结余 | O2: 目标值 | P2: 目标完成率
B3: 44562 | N3: ='2、存量资产-y'!B25+'3、存量资产-k'!B13 -> 5940295.2 | O3: 6500000 | P3: =N3/O3 -> 0.91389156
B4: 44593 | N4: ='2、存量资产-y'!C25+'3、存量资产-k'!C13 -> 7124085.8 | O4: 8000000 | P4: =N4/O4 -> 0.89051072
B5: 44682 | N5: ='2、存量资产-y'!F25+'3、存量资产-k'!F13 -> 7516913.3 | O5: 8000000 | P5: =N5/O5 -> 0.93961416
B6: 44713 | N6: ='2、存量资产-y'!G25+'3、存量资产-k'!G13 -> 8012723.5 | O6: 8000000 | P6: =N6/O6 -> 1.0015904
B7: 44743
B8: 44774 | N8: ='2、存量资产-y'!B31+'3、存量资产-k'!B19 -> 0
B9: 44805 | N9: ='2、存量资产-y'!B32+'3、存量资产-k'!B20 -> 0
B10: 44835 | N10: ='2、存量资产-y'!B33+'3、存量资产-k'!B21 -> 0
B11: 44866 | N11: ='2、存量资产-y'!B34+'3、存量资产-k'!B22 -> 0
B12: 44896 | N12: ='2、存量资产-y'!B35+'3、存量资产-k'!B23 -> 0
B13: 合计 | C13: =SUM(C3:C12) -> 0 | D13: =SUM(D3:D12) -> 0 | E13: =SUM(E3:E12) -> 0 | F13: =SUM(F3:F12) -> 0 | G13: =SUM(G3:G12) -> 0 | H13: =SUM(H3:H12) -> 0 | I13: =SUM(I3:I12) -> 0 | J13: =SUM(J3:J12) -> 0 | ... L13: =SUM(L3:L12) -> 0 | M13: =L13/J13 -> #DIV/0!
B14: 比例 | C14: =C13/$J13 -> #DIV/0! | D14: =D13/$J13 -> #DIV/0! | E14: =E13/$J13 -> #DIV/0! | F14: =F13/$J13 -> #DIV/0! | G14: =G13/$J13 -> #DIV/0! | H14: =H13/$J13 -> #DIV/0! | I14: =I13/$J13 -> #DIV/0! | J14: =J13/$J13 -> #DIV/0! | M14: =N13/J13 -> #DIV/0!

Sheet 2、存量资产-y
A1: 账户类型 | B1: 2026.1 | C1: 2026.2 | D1: 2026.3 | E1: 2026.4 | F1: 2026.5 | G1: 2026.6 | H1: 2026.7 | I1: 2026.8 | J1: 2026.9 | K1: 2026.1 | L1: 2026.11 | M1: 2026.12
A2: 海通 | B2: 11501 | C2: 11724 | F2: 11830.94 | G2: 11832.74
A3: 富钱包 | B3: 147022.86 | C3: 137526 | F3: 136231.75 | G3: 134522
A4: 兴业银行 | C4: 32584 | F4: 285165.96 | G4: 284212
A5: 招商 | B5: 8519.66 | C5: 988.8 | F5: 0 | G5: 10537
A6: 广发 | B6: 112738.66 | C6: 142072 | F6: 225255 | G6: 219972
A7: 支付宝 | B7: 32475.64 | C7: 32682 | F7: 29456.53 | G7: 29884
A8: 微信 | F8: 1471 | G8: 993.73
A9: 工商 | B9: 10749 | C9: 17075 | F9: 0 | G9: 0
A10: 温州 | B10: 500000 | C10: 500000 | D10: 500000 | E10: 500000 | F10: 500000 | G10: 500000 | H10: 500000 | I10: 500000 | J10: 500000 | K10: 500000 | L10: 500000 | M10: 500000
A11: 稠州 | B11: 500000 | C11: 500000 | D11: 500000 | E11: 500000 | F11: 500000 | G11: 500000 | H11: 500000 | I11: 500000 | J11: 500000 | K11: 500000 | L11: 500000 | M11: 500000
A12: 易方达 | B12: 19988.49 | C12: 19935 | F12: 19547.27 | G12: 19517
A13: 鹏华 | B13: 368986.86 | C13: 367684 | F13: 361890.96 | G13: 362216
A14: 华安 | B14: 32279 | C14: 32226 | F14: 31462 | G14: 31409
A15: 汇添富 | B15: 102080 | C15: 101693 | F15: 99885.88 | G15: 99798
A16: 合计 | B16: =SUM(B2:B15) -> 1846341.2 | C16: =SUM(C2:C15) -> 1896189.8 | D16: =SUM(D2:D15) -> 1000000 | E16: =SUM(E2:E15) -> 1000000 | F16: =SUM(F2:F15) -> 2202197.3 | G16: =SUM(G2:G15) -> 2204893.5 | H16: =SUM(H2:H15) -> 1000000 | I16: =SUM(I2:I15) -> 1000000 | ... M16: =SUM(M2:M15) -> 1000000
A17: 公积金 | B17: 135584 | C17: 135731 | F17: 136319 | G17: 136319
A18: 补充 | B18: 133109 | C18: 136839 | F18: 151759 | G18: 151759
A19: 农行 | B19: 22604 | C19: 22907 | F19: 22810 | G19: 22345
A20: 合计 | B20: =SUM(B17:B19) -> 291297 | C20: =SUM(C17:C19) -> 295477 | D20: =SUM(D17:D19) -> 0 | E20: =SUM(E17:E19) -> 0 | F20: =SUM(F17:F19) -> 310888 | G20: =SUM(G17:G19) -> 310423 | H20: =SUM(H17:H19) -> 0 | I20: =SUM(I17:I19) -> 0 | ... M20: =SUM(M17:M19) -> 0
A21: 房屋贷款
A22: 车贷
A23: 贷款总计 | B23: =SUM(B21:B22) -> 0 | C23: =SUM(C21:C22) -> 0 | D23: =SUM(D21:D22) -> 0 | E23: =SUM(E21:E22) -> 0 | F23: =SUM(F21:F22) -> 0 | G23: =SUM(G21:G22) -> 0 | H23: =SUM(H21:H22) -> 0 | I23: =SUM(I21:I22) -> 0 | ... M23: =SUM(M21:M22) -> 0
A24: 资产总计 | B24: =SUM(B16,B20) -> 2137638.2 | C24: =SUM(C16,C20) -> 2191666.8 | D24: =SUM(D16,D20) -> 1000000 | E24: =SUM(E16,E20) -> 1000000 | F24: =SUM(F16,F20) -> 2513085.3 | G24: =SUM(G16,G20) -> 2515316.5 | H24: =SUM(H16,H20) -> 1000000 | I24: =SUM(I16,I20) -> 1000000 | ... M24: =SUM(M16,M20) -> 1000000
A25: 净资产 | B25: =B24-B23 -> 2137638.2 | C25: =C24-C23 -> 2191666.8 | D25: =D24-D23 -> 1000000 | E25: =E24-E23 -> 1000000 | F25: =F24-F23 -> 2513085.3 | G25: =G24-G23 -> 2515316.5 | H25: =H24-H23 -> 1000000 | I25: =I24-I23 -> 1000000 | ... M25: =M24-M23 -> 1000000

Sheet 3、存量资产-k
A1: 账户类型 | B1: 2026.1 | C1: 2026.2 | D1: 2026.3 | E1: 2026.4 | F1: 2026.5 | G1: 2026.6 | H1: 2026.7 | I1: 2026.8 | J1: 2026.9 | K1: 2026.1 | L1: 2026.11 | M1: 2026.12
A2: 美元资产 | B2: =490768*7 -> 3435376 | C2: =592893*7 -> 4150251 | F2: =602516*7 -> 4217612 | G2: =708815*6.7838 -> 4808459.2
A3: 人民币现金 | B3: =155000+43677+1565+1234+307 -> 201783 | C3: =396647+1521+1154+304+198050 -> 597676 | F3: 626003 | G3: =58877.21+476635.39 -> 535512.6
A4: 人民币基金 | B4: 3750 | C4: 3883 | F4: =15023+3705 -> 18728 | G4: =3499.22+33235 -> 36734.22
A5: 合计 | B5: =SUM(B2:B4) -> 3640909 | C5: =SUM(C2:C4) -> 4751810 | D5: =SUM(D2:D4) -> 0 | E5: =SUM(E2:E4) -> 0 | F5: =SUM(F2:F4) -> 4862343 | G5: =SUM(G2:G4) -> 5380706 | H5: =SUM(H2:H4) -> 0 | I5: =SUM(I2:I4) -> 0 | ... M5: =SUM(M2:M4) -> 0
A6: 公积金 | B6: =33429+58692+45931 -> 138052 | C6: =33429+58692+64303 -> 156424 | F6: =23429+58692+35826 -> 117947 | G6: =13429+58692+21128 -> 93249
A7: 个人养老金 | B7: 23696 | C7: 24185 | F7: 23538 | G7: 23452
A8: 合计 | B8: =SUM(B6:B7) -> 161748 | C8: =SUM(C6:C7) -> 180609 | D8: =SUM(D6:D7) -> 0 | E8: =SUM(E6:E7) -> 0 | F8: =SUM(F6:F7) -> 141485 | G8: =SUM(G6:G7) -> 116701 | H8: =SUM(H6:H7) -> 0 | I8: =SUM(I6:I7) -> 0 | ... M8: =SUM(M6:M7) -> 0
A9: 房屋贷款
A10: 车贷
A11: 贷款总计
A12: 资产总计 | B12: =B8+B5 -> 3802657 | C12: =C8+C5 -> 4932419 | D12: =D8+D5 -> 0 | E12: =E8+E5 -> 0 | F12: =F8+F5 -> 5003828 | G12: =G8+G5 -> 5497407 | H12: =H8+H5 -> 0 | I12: =I8+I5 -> 0 | ... M12: =M8+M5 -> 0
A13: 净资产 | B13: =B12-B11 -> 3802657 | C13: =C12-C11 -> 4932419 | D13: =D12-D11 -> 0 | E13: =E12-E11 -> 0 | F13: =F12-F11 -> 5003828 | G13: =G12-G11 -> 5497407 | H13: =H12-H11 -> 0 | I13: =I12-I11 -> 0 | ... M13: =M12-M11 -> 0
